pymimir-0.13.59.dist-info/RECORD
pymimir-0.13.59.dist-info/WHEEL
pymimir-0.13.59.dist-info/top_level.txt
pymimir-0.13.59.dist-info/METADATA
pymimir-0.13.59.dist-info/licenses/LICENSE
pymimir/__init__.py
pymimir/wrapper_heuristics.py
pymimir/wrapper_search_gbfs.py
pymimir/wrapper_search_brfs.py
pymimir/wrapper_search_astar.py
pymimir/wrapper_search_width.py
pymimir/wrapper_formalism.py
pymimir/wrapper_search.py
pymimir/pymimir.cpython-310-darwin.so
pymimir/wrapper_datasets.py
pymimir/advanced/__init__.pyi
pymimir/advanced/__init__.py
pymimir/advanced/datasets/__init__.pyi
pymimir/advanced/datasets/__init__.py
pymimir/advanced/languages/__init__.pyi
pymimir/advanced/languages/__init__.py
pymimir/advanced/languages/description_logics/__init__.pyi
pymimir/advanced/languages/description_logics/__init__.py
pymimir/advanced/languages/general_policies/__init__.pyi
pymimir/advanced/languages/general_policies/__init__.py
pymimir/advanced/search/__init__.pyi
pymimir/advanced/search/__init__.py
pymimir/advanced/common/__init__.pyi
pymimir/advanced/common/__init__.py
pymimir/advanced/formalism/__init__.pyi
pymimir/advanced/formalism/__init__.py
pymimir/advanced/graphs/__init__.pyi
pymimir/advanced/graphs/__init__.py
