Metadata-Version: 2.1
Name: pymimir
Version: 0.13.59
Summary: Mimir planning library
Home-page: https://github.com/simon-stahlberg/mimir
Author: Simon Stahlberg, Dominik Drexler
Author-email: simon.stahlberg@gmail.com, dominik.drexler@liu.se
License-File: LICENSE
Requires-Dist: cmake>=3.21
Provides-Extra: test
Requires-Dist: pytest; extra == "test"
